{
    "animation": [],
    "animation_direction_idle": "normal",
    "animation_direction_screaming": "normal",
    "animation_direction_talking": "reverse",
    "animation_idle": true,
    "animation_iteration_idle": 0,
    "animation_iteration_screaming": 0,
    "animation_iteration_talking": 0,
    "animation_name_idle": "None",
    "animation_name_screaming": "wobble",
    "animation_name_talking": "gelatine2",
    "animation_pacing_idle": "ease-in-out",
    "animation_pacing_screaming": "ease-in-out",
    "animation_pacing_talking": "ease-in-out",
    "animation_speed_idle": 6.0,
    "animation_speed_screaming": 0.5,
    "animation_speed_talking": 0.5,
    "blinking": "ignore",
    "buttons": 0,
    "chords": [],
    "controller": [
        "ignore"
    ],
    "css": "",
    "cursor": true,
    "cursorScaleX": 0.003,
    "cursorScaleY": 0.004,
    "deadzone": 0.055,
    "deg": 90,
    "degRight": 90,
    "degWhammy": 0,
    "degZoom": 90,
    "filename": "hairback_328.png",
    "hotkeys": [],
    "invertAxis": 0,
    "invert_mouse_x": 0,
    "invert_mouse_y": 1,
    "mode": "display",
    "originX": 0,
    "originXright": 0,
    "originXwhammy": 0,
    "originXzoom": 0,
    "originY": 0,
    "originYright": 0,
    "originYwhammy": 0,
    "originYzoom": 0,
    "parent_folder": "hairback",
    "player": 1,
    "player2": 1,
    "posBothX": 0,
    "posBothY": 0,
    "posGuitarDownX": 0,
    "posGuitarDownY": 0,
    "posGuitarUpX": 0,
    "posGuitarUpY": 0,
    "posLeftX": 0,
    "posLeftY": 0,
    "posRightX": 0,
    "posRightY": 0,
    "posX": 0,
    "posY": 0,
    "posZ": 2,
    "rotation": 0,
    "rotationBoth": 0,
    "rotationGuitarDown": 0,
    "rotationGuitarUp": 0,
    "rotationLeft": 0,
    "rotationRight": 0,
    "sizeX": 600,
    "sizeY": 600,
    "talking": "ignore",
    "thumbnail_path": "Assets/Chereverie/hairback/thumbs/hairback_328.png",
    "title": "hairback_328.png",
    "track_mouse_x": 1,
    "track_mouse_y": 1,
    "use_css": false,
    "move": true
}